<screen name="glass" position="center,center" size="1800,960" flags="wfNoBorder" backgroundColor="#024A4A">
		<widget source="Title" render="Label" position="20,20" size="1050,60" font="SRegular;39" foregroundColor="#FFFFFF" valign="top" transparent="1"/>
		<ePixmap pixmap="/usr/lib/enigma2/python/Plugins/Extensions/Enigmawelt/img/bg_fhd.png" position="0,0" size="1920,89" zPosition="-5"/>
		<ePixmap pixmap="/usr/lib/enigma2/python/Plugins/Extensions/Enigmawelt/img/bg_fhd.png" position="0,871" size="1920,89" zPosition="-5"/>
		<ePixmap pixmap="/usr/lib/enigma2/python/Plugins/Extensions/Enigmawelt/img/logo.png" position="1720,11" size="68,68" alphatest="blend" scale="1"/>
		<eLabel position="0,90" size="1800,780" backgroundColor="#024A4A" zPosition="-1"/>
		<eLabel position="1630,25" size="100,40" text="v1.4" font="SRegular;24" foregroundColor="#FFFFFF" halign="center" valign="center" transparent="1"/>
		<widget source="movielist" render="Listbox" position="18,108" size="1070,750" foregroundColor="#FFFFFF" foregroundColorSelected="#FFFFFF" backgroundColorSelected="#038181" scrollbarMode="showOnDemand" scrollbarWidth="6" scrollbarForegroundColor="#00C0C0" scrollbarBackgroundColor="#024A4A" transparent="1">
			<convert type="TemplatedMultiContent">{"template": [ MultiContentEntryText(pos=(6,0), size=(1041,45), font=0, text=0, flags=RT_HALIGN_LEFT|RT_VALIGN_CENTER)], "fonts": [gFont("SRegular",33)], "itemHeight": 50 }</convert>
		</widget>
		<widget name="cover" position="1095,100" size="690,325" alphatest="blend" conditional="cover" scaleFlags="scaleCenter" transparent="1"/>
		<widget name="description" position="1105,435" size="680,420" font="SRegular;28" foregroundColor="#FFFFFF" scrollbarWidth="6" scrollbarForegroundColor="#AFAFAF" transparent="1"/>
		<eLabel position="1660,878" size="118,75" text="EXIT" font="SRegular;36" foregroundColor="#000000" backgroundColor="#FFFFFF" halign="center" valign="center" />
		<eLabel position="1517,878" size="118,75" text="OK" font="SRegular;36" foregroundColor="#000000" backgroundColor="#FFFFFF" halign="center" valign="center" />
		<eLabel position="1374,878" size="118,75" text="MENU" font="SRegular;36" foregroundColor="#000000" backgroundColor="#FFFFFF" halign="center" valign="center" />
		<eLabel position="25,895" size="8,45" backgroundColor="#0005CD"/>
		<eLabel position="42,895" size="170,39" text="Beenden" font="SRegular;30" foregroundColor="#FFFFFF" valign="center" transparent="1"/>
		<eLabel position="225,895" size="8,45" backgroundColor="#15FF0A"/>
		<eLabel position="242,895" size="170,39" text="Play" font="SRegular;30" foregroundColor="#FFFFFF" valign="center" transparent="1"/>
		<eLabel position="426,895" size="8,45" backgroundColor="#FDFE0C"/>
		<eLabel position="442,895" size="170,39" text="Suche" font="SRegular;30" foregroundColor="#FFFFFF" transparent="1"/>
		<eLabel position="625,895" size="8,45" backgroundColor="#1B0BF4"/>
		<eLabel position="642,895" size="170,39" text="Download" font="SRegular;30" foregroundColor="#FFFFFF" valign="center" transparent="1"/>
		<widget name="progress" position="1150,58" size="480,15" foregroundColor="#FFFFFF" borderColor="#FFFFFF" backgroundColor="#024A4A" borderWidth="1" transparent="0"/>
		<widget name="DownloadLabel" position="1140,10" size="540,39" font="SRegular;21" foregroundColor="#FFFFFF" halign="center" transparent="1"/>
		</screen>